{
    "lines": [
        {
            "data": {
                "end": [
                    0.0,
                    0.0,
                    0.0
                ],
                "start": [
                    0.0,
                    0.0,
                    -2.5
                ]
            },
            "dtype": "compas.geometry/Line",
            "guid": "19e5ee76-7916-4569-9a4b-8e7355eaaae6"
        },
        {
            "data": {
                "end": [
                    0.0,
                    5.0,
                    0.0
                ],
                "start": [
                    0.0,
                    5.0,
                    -2.5
                ]
            },
            "dtype": "compas.geometry/Line",
            "guid": "8b502977-964f-4dcf-a95b-3357e784f407"
        },
        {
            "data": {
                "end": [
                    3.1,
                    5.0,
                    0.0
                ],
                "start": [
                    3.1,
                    5.0,
                    -2.5
                ]
            },
            "dtype": "compas.geometry/Line",
            "guid": "498ed7f6-0d02-4fe9-a594-21fba3b1981a"
        },
        {
            "data": {
                "end": [
                    3.1,
                    0.0,
                    0.0
                ],
                "start": [
                    3.1,
                    0.0,
                    -2.5
                ]
            },
            "dtype": "compas.geometry/Line",
            "guid": "ee4dec8d-c873-42dc-9d2f-dd53392a14df"
        },
        {
            "data": {
                "end": [
                    0.0,
                    5.0,
                    0.0
                ],
                "start": [
                    0.0,
                    0.0,
                    0.0
                ]
            },
            "dtype": "compas.geometry/Line",
            "guid": "8d10f70f-1aae-40ca-8dd4-daa86469ad70"
        },
        {
            "data": {
                "end": [
                    3.1,
                    0.0,
                    0.0
                ],
                "start": [
                    3.1,
                    5.0,
                    0.0
                ]
            },
            "dtype": "compas.geometry/Line",
            "guid": "a90ee7b5-0ed5-41a0-87d2-d32d53bd672f"
        },
        {
            "data": {
                "end": [
                    3.1,
                    5.0,
                    0.0
                ],
                "start": [
                    0.0,
                    5.0,
                    0.0
                ]
            },
            "dtype": "compas.geometry/Line",
            "guid": "941674ef-db08-4d13-bb4c-5b2eec8c016c"
        },
        {
            "data": {
                "end": [
                    0.0,
                    0.0,
                    0.0
                ],
                "start": [
                    3.1,
                    0.0,
                    0.0
                ]
            },
            "dtype": "compas.geometry/Line",
            "guid": "7d610670-669b-4f1c-b984-52373cae4850"
        }
    ],
    "meshes": [
        {
            "data": {
                "attributes": {},
                "default_edge_attributes": {},
                "default_face_attributes": {},
                "default_vertex_attributes": {
                    "x": 0.0,
                    "y": 0.0,
                    "z": 0.0
                },
                "edgedata": {},
                "face": {
                    "0": [
                        0,
                        1,
                        2,
                        3
                    ]
                },
                "facedata": {
                    "0": {}
                },
                "max_face": 0,
                "max_vertex": 3,
                "vertex": {
                    "0": {
                        "x": 0.0,
                        "y": 0.0,
                        "z": 0.0
                    },
                    "1": {
                        "x": 0.0,
                        "y": 5.0,
                        "z": 0.0
                    },
                    "2": {
                        "x": 3.1,
                        "y": 5.0,
                        "z": 0.0
                    },
                    "3": {
                        "x": 3.1,
                        "y": 0.0,
                        "z": 0.0
                    }
                }
            },
            "dtype": "compas.datastructures/Mesh",
            "guid": "35426cb1-be40-4bbb-a9a5-960217257bca"
        }
    ]
}